lipo/__init__.py
lipo/hyperparameter.py
lipo/optimizer.py
lipo-1.2.2.dist-info/LICENSE
lipo-1.2.2.dist-info/WHEEL
lipo-1.2.2.dist-info/METADATA
lipo-1.2.2.dist-info/RECORD
