Metadata-Version: 2.1
Name: lipo
Version: 1.2.2
Summary: Global, derivative- and parameter-free (hyperparameter) optimization
Home-page: https://github.com/jdb78/lipo
Author: Jan Beitner
Requires-Python: >=3.6.1,<4.0.0
Classifier: Development Status :: 4 - Beta
Classifier: Intended Audience :: Developers
Classifier: License :: OSI Approved :: MIT License
Classifier: Programming Language :: Python :: 3
Classifier: Programming Language :: Python :: 3.7
Classifier: Programming Language :: Python :: 3.8
Classifier: Programming Language :: Python :: 3.9
Provides-Extra: github-actions
Requires-Dist: dlib (>=19.21.1,<20.0.0)
Requires-Dist: pytest-github-actions-annotate-failures; extra == "github-actions"
Requires-Dist: scikit-learn (>=0.22.1)
Requires-Dist: tqdm (>=4.55.0,<5.0.0)
Project-URL: Repository, https://github.com/jdb78/lipo
